pyGroupedTransforms/CWWTtools.py
pyGroupedTransforms/DeferredLinearOperator.py
pyGroupedTransforms/GroupedCoefficients.py
pyGroupedTransforms/GroupedTransform.py
pyGroupedTransforms/GroupedTransforms.py
pyGroupedTransforms/NFCTtools.py
pyGroupedTransforms/NFFTtools.py
pyGroupedTransforms/NFMTtools.py
pyGroupedTransforms/__init__.py
pyGroupedTransforms/cardinal_bspline.py
pygroupedtransforms-1.0.0.dist-info/METADATA
pygroupedtransforms-1.0.0.dist-info/WHEEL
pygroupedtransforms-1.0.0.dist-info/licenses/LICENSE
pygroupedtransforms-1.0.0.dist-info/RECORD
