Metadata-Version: 2.4
Name: pyGroupedTransforms
Version: 1.0.0
Summary: Python implementation of Grouped Transforms
Project-URL: Homepage, https://github.com/NFFT/pyGroupedTransforms
Author-email: Felix Wirth <fwi012001@gmail.com>
Maintainer-email: Pascal Schröter <pascal.schroeter@mathematik.tu-chemnitz.de>
License-File: LICENSE
Requires-Python: >=3.9
Requires-Dist: numpy>=2.0.0
Requires-Dist: pynfft3>=0.2.2
Requires-Dist: scipy>=1.16.0
